{
  "v": "5.9.5",
  "fr": 30,
  "ip": 0,
  "op": 73,
  "w": 1019,
  "h": 314,
  "nm": "Text Animation (25-12-2024)",
  "ddd": 0,
  "assets": [],
  "fonts": {
    "list": [
      {
        "fName": "Sora-Bold",
        "fFamily": "Sora",
        "fStyle": "Bold",
        "ascent": 72.9995727539062
      }
    ]
  },
  "layers": [
    {
      "ddd": 0,
      "ind": 1,
      "ty": 3,
      "nm": "Primary Null 1",
      "sr": 1,
      "ks": {
        "o": { "a": 0, "k": 0, "ix": 11 },
        "r": { "a": 0, "k": 0, "ix": 10 },
        "p": { "a": 0, "k": [509, 132.633, 0], "ix": 2, "l": 2 },
        "a": { "a": 0, "k": [50, 50, 0], "ix": 1, "l": 2 },
        "s": { "a": 0, "k": [100, 100, 100], "ix": 6, "l": 2 }
      },
      "ao": 0,
      "ip": 0,
      "op": 900.9013671875,
      "st": 0,
      "bm": 0
    },
    {
      "ddd": 0,
      "ind": 2,
      "ty": 3,
      "nm": "Null Collect  1",
      "parent": 1,
      "sr": 1,
      "ks": {
        "o": { "a": 0, "k": 0, "ix": 11 },
        "r": { "a": 0, "k": 0, "ix": 10 },
        "p": {
          "a": 1,
          "k": [
            {
              "i": { "x": 0.176, "y": 1 },
              "o": { "x": 0.333, "y": 0 },
              "t": 2,
              "s": [50, 50, 0],
              "to": [0, 0, 0],
              "ti": [0, 0, 0]
            },
            { "t": 34, "s": [50, 80, 0] }
          ],
          "ix": 2,
          "l": 2
        },
        "a": { "a": 0, "k": [50, 50, 0], "ix": 1, "l": 2 },
        "s": { "a": 0, "k": [100, 100, 100], "ix": 6, "l": 2 }
      },
      "ao": 0,
      "ip": 0,
      "op": 900.9013671875,
      "st": 0,
      "bm": 0
    },
    {
      "ddd": 0,
      "ind": 3,
      "ty": 3,
      "nm": "Null 1",
      "parent": 2,
      "sr": 1,
      "ks": {
        "o": { "a": 0, "k": 0, "ix": 11 },
        "r": {
          "a": 1,
          "k": [
            {
              "i": { "x": [0.667], "y": [1] },
              "o": { "x": [0.333], "y": [0] },
              "t": 7.188,
              "s": [0]
            },
            {
              "i": { "x": [0.667], "y": [1] },
              "o": { "x": [0.333], "y": [0] },
              "t": 14.5,
              "s": [-23]
            },
            {
              "i": { "x": [0.667], "y": [1] },
              "o": { "x": [0.333], "y": [0] },
              "t": 21.203,
              "s": [10]
            },
            { "t": 28.1875, "s": [0] }
          ],
          "ix": 10
        },
        "p": { "a": 0, "k": [-383.066, 17.319, 0], "ix": 2, "l": 2 },
        "a": { "a": 0, "k": [100, 100, 0], "ix": 1, "l": 2 },
        "s": { "a": 0, "k": [20, 20, 100], "ix": 6, "l": 2 }
      },
      "ao": 0,
      "ip": 0,
      "op": 900,
      "st": 0,
      "bm": 0
    },
    {
      "ddd": 0,
      "ind": 4,
      "ty": 4,
      "nm": "Path",
      "parent": 3,
      "sr": 1,
      "ks": {
        "o": { "a": 0, "k": 100, "ix": 11 },
        "r": { "a": 0, "k": 0, "ix": 10 },
        "p": { "a": 0, "k": [126.347, 80.776, 0], "ix": 2, "l": 2 },
        "a": { "a": 0, "k": [28.077, 22.275, 0], "ix": 1, "l": 2 },
        "s": { "a": 0, "k": [500, 500, 100], "ix": 6, "l": 2 }
      },
      "ao": 0,
      "shapes": [
        {
          "ty": "gr",
          "it": [
            {
              "ind": 0,
              "ty": "sh",
              "ix": 1,
              "ks": {
                "a": 0,
                "k": {
                  "i": [
                    [0, 0],
                    [0, 0]
                  ],
                  "o": [
                    [0, 0],
                    [0, 0]
                  ],
                  "v": [
                    [28.077, 22.275],
                    [25.522, 6.225]
                  ],
                  "c": false
                },
                "ix": 2
              },
              "nm": "Path 1",
              "mn": "ADBE Vector Shape - Group",
              "hd": false
            },
            {
              "ty": "st",
              "c": {
                "a": 0,
                "k": [0.46274510026, 0.188235297799, 1, 1],
                "ix": 3
              },
              "o": { "a": 0, "k": 100, "ix": 4 },
              "w": { "a": 0, "k": 3, "ix": 5 },
              "lc": 2,
              "lj": 1,
              "ml": 4,
              "bm": 0,
              "nm": "Stroke 1",
              "mn": "ADBE Vector Graphic - Stroke",
              "hd": false
            },
            {
              "ty": "tr",
              "p": { "a": 0, "k": [0, 0], "ix": 2 },
              "a": { "a": 0, "k": [0, 0], "ix": 1 },
              "s": { "a": 0, "k": [100, 100], "ix": 3 },
              "r": { "a": 0, "k": 0, "ix": 6 },
              "o": { "a": 0, "k": 100, "ix": 7 },
              "sk": { "a": 0, "k": 0, "ix": 4 },
              "sa": { "a": 0, "k": 0, "ix": 5 },
              "nm": "Transform"
            }
          ],
          "nm": "Path",
          "np": 3,
          "cix": 2,
          "bm": 0,
          "ix": 1,
          "mn": "ADBE Vector Group",
          "hd": false
        },
        {
          "ty": "tm",
          "s": { "a": 0, "k": 0, "ix": 1 },
          "e": {
            "a": 1,
            "k": [
              {
                "i": { "x": [0.3], "y": [1] },
                "o": { "x": [0.333], "y": [0] },
                "t": 2,
                "s": [0]
              },
              { "t": 16, "s": [100] }
            ],
            "ix": 2
          },
          "o": { "a": 0, "k": 0, "ix": 3 },
          "m": 1,
          "ix": 2,
          "nm": "Trim Paths 1",
          "mn": "ADBE Vector Filter - Trim",
          "hd": false
        }
      ],
      "ip": 0,
      "op": 900.900900900901,
      "st": 0,
      "ct": 1,
      "bm": 0
    },
    {
      "ddd": 0,
      "ind": 5,
      "ty": 4,
      "nm": "Path",
      "parent": 3,
      "sr": 1,
      "ks": {
        "o": { "a": 0, "k": 100, "ix": 11 },
        "r": { "a": 0, "k": 0, "ix": 10 },
        "p": { "a": 0, "k": [94.312, 94.326, 0], "ix": 2, "l": 2 },
        "a": { "a": 0, "k": [21.67, 24.985, 0], "ix": 1, "l": 2 },
        "s": { "a": 0, "k": [500, 500, 100], "ix": 6, "l": 2 }
      },
      "ao": 0,
      "shapes": [
        {
          "ty": "gr",
          "it": [
            {
              "ind": 0,
              "ty": "sh",
              "ix": 1,
              "ks": {
                "a": 0,
                "k": {
                  "i": [
                    [0, 0],
                    [0, 0]
                  ],
                  "o": [
                    [0, 0],
                    [0, 0]
                  ],
                  "v": [
                    [21.67, 24.985],
                    [15.926, 16.956]
                  ],
                  "c": false
                },
                "ix": 2
              },
              "nm": "Path 1",
              "mn": "ADBE Vector Shape - Group",
              "hd": false
            },
            {
              "ty": "st",
              "c": {
                "a": 0,
                "k": [0.46274510026, 0.188235297799, 1, 1],
                "ix": 3
              },
              "o": { "a": 0, "k": 100, "ix": 4 },
              "w": { "a": 0, "k": 3, "ix": 5 },
              "lc": 2,
              "lj": 1,
              "ml": 4,
              "bm": 0,
              "nm": "Stroke 1",
              "mn": "ADBE Vector Graphic - Stroke",
              "hd": false
            },
            {
              "ty": "tr",
              "p": { "a": 0, "k": [0, 0], "ix": 2 },
              "a": { "a": 0, "k": [0, 0], "ix": 1 },
              "s": { "a": 0, "k": [100, 100], "ix": 3 },
              "r": { "a": 0, "k": 0, "ix": 6 },
              "o": { "a": 0, "k": 100, "ix": 7 },
              "sk": { "a": 0, "k": 0, "ix": 4 },
              "sa": { "a": 0, "k": 0, "ix": 5 },
              "nm": "Transform"
            }
          ],
          "nm": "Path",
          "np": 3,
          "cix": 2,
          "bm": 0,
          "ix": 1,
          "mn": "ADBE Vector Group",
          "hd": false
        },
        {
          "ty": "tm",
          "s": { "a": 0, "k": 0, "ix": 1 },
          "e": {
            "a": 1,
            "k": [
              {
                "i": { "x": [0.286], "y": [1] },
                "o": { "x": [0.333], "y": [0] },
                "t": 5.5,
                "s": [0]
              },
              { "t": 19, "s": [100] }
            ],
            "ix": 2
          },
          "o": { "a": 0, "k": 0, "ix": 3 },
          "m": 1,
          "ix": 2,
          "nm": "Trim Paths 1",
          "mn": "ADBE Vector Filter - Trim",
          "hd": false
        }
      ],
      "ip": 0,
      "op": 900.900900900901,
      "st": 0,
      "ct": 1,
      "bm": 0
    },
    {
      "ddd": 0,
      "ind": 6,
      "ty": 4,
      "nm": "Path",
      "parent": 3,
      "sr": 1,
      "ks": {
        "o": { "a": 0, "k": 100, "ix": 11 },
        "r": { "a": 0, "k": 0, "ix": 10 },
        "p": { "a": 0, "k": [62.732, 122.906, 0], "ix": 2, "l": 2 },
        "a": { "a": 0, "k": [15.354, 30.701, 0], "ix": 1, "l": 2 },
        "s": { "a": 0, "k": [500, 500, 100], "ix": 6, "l": 2 }
      },
      "ao": 0,
      "shapes": [
        {
          "ty": "gr",
          "it": [
            {
              "ind": 0,
              "ty": "sh",
              "ix": 1,
              "ks": {
                "a": 0,
                "k": {
                  "i": [
                    [0, 0],
                    [0, 0]
                  ],
                  "o": [
                    [0, 0],
                    [0, 0]
                  ],
                  "v": [
                    [15.354, 30.701],
                    [1.648, 20.473]
                  ],
                  "c": false
                },
                "ix": 2
              },
              "nm": "Path 1",
              "mn": "ADBE Vector Shape - Group",
              "hd": false
            },
            {
              "ty": "st",
              "c": {
                "a": 0,
                "k": [0.46274510026, 0.188235297799, 1, 1],
                "ix": 3
              },
              "o": { "a": 0, "k": 100, "ix": 4 },
              "w": { "a": 0, "k": 3, "ix": 5 },
              "lc": 2,
              "lj": 1,
              "ml": 4,
              "bm": 0,
              "nm": "Stroke 1",
              "mn": "ADBE Vector Graphic - Stroke",
              "hd": false
            },
            {
              "ty": "tr",
              "p": { "a": 0, "k": [0, 0], "ix": 2 },
              "a": { "a": 0, "k": [0, 0], "ix": 1 },
              "s": { "a": 0, "k": [100, 100], "ix": 3 },
              "r": { "a": 0, "k": 0, "ix": 6 },
              "o": { "a": 0, "k": 100, "ix": 7 },
              "sk": { "a": 0, "k": 0, "ix": 4 },
              "sa": { "a": 0, "k": 0, "ix": 5 },
              "nm": "Transform"
            }
          ],
          "nm": "Path",
          "np": 3,
          "cix": 2,
          "bm": 0,
          "ix": 1,
          "mn": "ADBE Vector Group",
          "hd": false
        },
        {
          "ty": "tm",
          "s": { "a": 0, "k": 0, "ix": 1 },
          "e": {
            "a": 1,
            "k": [
              {
                "i": { "x": [0.286], "y": [1] },
                "o": { "x": [0.333], "y": [0] },
                "t": 9,
                "s": [0]
              },
              { "t": 22.5, "s": [100] }
            ],
            "ix": 2
          },
          "o": { "a": 0, "k": 0, "ix": 3 },
          "m": 1,
          "ix": 2,
          "nm": "Trim Paths 1",
          "mn": "ADBE Vector Filter - Trim",
          "hd": false
        }
      ],
      "ip": 0,
      "op": 900.900900900901,
      "st": 0,
      "ct": 1,
      "bm": 0
    },
    {
      "ddd": 0,
      "ind": 7,
      "ty": 4,
      "nm": "Path",
      "parent": 2,
      "sr": 1,
      "ks": {
        "o": { "a": 0, "k": 100, "ix": 11 },
        "r": { "a": 0, "k": 0, "ix": 10 },
        "p": { "a": 0, "k": [322.777, 88.681, 0], "ix": 2, "l": 2 },
        "a": { "a": 0, "k": [728.651, 97.482, 0], "ix": 1, "l": 2 },
        "s": { "a": 0, "k": [100, 100, 100], "ix": 6, "l": 2 }
      },
      "ao": 0,
      "shapes": [
        {
          "ty": "gr",
          "it": [
            {
              "ind": 0,
              "ty": "sh",
              "ix": 1,
              "ks": {
                "a": 0,
                "k": {
                  "i": [
                    [0, 0],
                    [-96.228, -13.62]
                  ],
                  "o": [
                    [71.395, -7.045],
                    [0, 0]
                  ],
                  "v": [
                    [569.453, 101.45],
                    [887.848, 101.45]
                  ],
                  "c": false
                },
                "ix": 2
              },
              "nm": "Path 1",
              "mn": "ADBE Vector Shape - Group",
              "hd": false
            },
            {
              "ty": "st",
              "c": {
                "a": 0,
                "k": [0.403921574354, 0.384313732386, 0.996078431606, 1],
                "ix": 3
              },
              "o": { "a": 0, "k": 100, "ix": 4 },
              "w": { "a": 0, "k": 2.818, "ix": 5 },
              "lc": 2,
              "lj": 1,
              "ml": 4,
              "bm": 0,
              "nm": "Stroke 1",
              "mn": "ADBE Vector Graphic - Stroke",
              "hd": false
            },
            {
              "ty": "tr",
              "p": { "a": 0, "k": [0, 0], "ix": 2 },
              "a": { "a": 0, "k": [0, 0], "ix": 1 },
              "s": { "a": 0, "k": [100, 100], "ix": 3 },
              "r": { "a": 0, "k": 0, "ix": 6 },
              "o": { "a": 0, "k": 100, "ix": 7 },
              "sk": { "a": 0, "k": 0, "ix": 4 },
              "sa": { "a": 0, "k": 0, "ix": 5 },
              "nm": "Transform"
            }
          ],
          "nm": "Path",
          "np": 3,
          "cix": 2,
          "bm": 0,
          "ix": 1,
          "mn": "ADBE Vector Group",
          "hd": false
        },
        {
          "ty": "tm",
          "s": { "a": 0, "k": 0, "ix": 1 },
          "e": {
            "a": 1,
            "k": [
              {
                "i": { "x": [0.317], "y": [1] },
                "o": { "x": [0.333], "y": [0] },
                "t": 11.184,
                "s": [0]
              },
              { "t": 37, "s": [100] }
            ],
            "ix": 2
          },
          "o": { "a": 0, "k": 0, "ix": 3 },
          "m": 1,
          "ix": 2,
          "nm": "Trim Paths 1",
          "mn": "ADBE Vector Filter - Trim",
          "hd": false
        }
      ],
      "ip": 0,
      "op": 900.900900900901,
      "st": 0,
      "ct": 1,
      "bm": 0
    },
    {
      "ddd": 0,
      "ind": 8,
      "ty": 4,
      "nm": "Path",
      "parent": 2,
      "sr": 1,
      "ks": {
        "o": { "a": 0, "k": 100, "ix": 11 },
        "r": { "a": 0, "k": 0, "ix": 10 },
        "p": { "a": 0, "k": [323.716, 81.167, 0], "ix": 2, "l": 2 },
        "a": { "a": 0, "k": [729.589, 89.968, 0], "ix": 1, "l": 2 },
        "s": { "a": 0, "k": [100, 100, 100], "ix": 6, "l": 2 }
      },
      "ao": 0,
      "shapes": [
        {
          "ty": "gr",
          "it": [
            {
              "ind": 0,
              "ty": "sh",
              "ix": 1,
              "ks": {
                "a": 0,
                "k": {
                  "i": [
                    [0, 0],
                    [-101.905, -13.619]
                  ],
                  "o": [
                    [75.607, -7.045],
                    [0, 0]
                  ],
                  "v": [
                    [561, 93.936],
                    [898.179, 93.936]
                  ],
                  "c": false
                },
                "ix": 2
              },
              "nm": "Path 1",
              "mn": "ADBE Vector Shape - Group",
              "hd": false
            },
            {
              "ty": "st",
              "c": {
                "a": 0,
                "k": [0.403921574354, 0.384313732386, 0.996078431606, 1],
                "ix": 3
              },
              "o": { "a": 0, "k": 100, "ix": 4 },
              "w": { "a": 0, "k": 2.818, "ix": 5 },
              "lc": 2,
              "lj": 1,
              "ml": 4,
              "bm": 0,
              "nm": "Stroke 1",
              "mn": "ADBE Vector Graphic - Stroke",
              "hd": false
            },
            {
              "ty": "tr",
              "p": { "a": 0, "k": [0, 0], "ix": 2 },
              "a": { "a": 0, "k": [0, 0], "ix": 1 },
              "s": { "a": 0, "k": [100, 100], "ix": 3 },
              "r": { "a": 0, "k": 0, "ix": 6 },
              "o": { "a": 0, "k": 100, "ix": 7 },
              "sk": { "a": 0, "k": 0, "ix": 4 },
              "sa": { "a": 0, "k": 0, "ix": 5 },
              "nm": "Transform"
            }
          ],
          "nm": "Path",
          "np": 3,
          "cix": 2,
          "bm": 0,
          "ix": 1,
          "mn": "ADBE Vector Group",
          "hd": false
        },
        {
          "ty": "tm",
          "s": { "a": 0, "k": 0, "ix": 1 },
          "e": {
            "a": 1,
            "k": [
              {
                "i": { "x": [0.317], "y": [1] },
                "o": { "x": [0.333], "y": [0] },
                "t": 6.97,
                "s": [0]
              },
              { "t": 32.78515625, "s": [100] }
            ],
            "ix": 2
          },
          "o": { "a": 0, "k": 0, "ix": 3 },
          "m": 1,
          "ix": 2,
          "nm": "Trim Paths 1",
          "mn": "ADBE Vector Filter - Trim",
          "hd": false
        }
      ],
      "ip": 0,
      "op": 900.900900900901,
      "st": 0,
      "ct": 1,
      "bm": 0
    },
    {
      "ddd": 0,
      "ind": 9,
      "ty": 5,
      "nm": "Get Started with Our Flexible Plans",
      "parent": 10,
      "sr": 1,
      "ks": {
        "o": {
          "a": 1,
          "k": [
            {
              "i": { "x": [0.087], "y": [1] },
              "o": { "x": [0.333], "y": [0] },
              "t": 0,
              "s": [0]
            },
            { "t": 10, "s": [100] }
          ],
          "ix": 11
        },
        "r": { "a": 0, "k": 0, "ix": 10 },
        "p": { "a": 0, "k": [455.874, 47.324, 0], "ix": 2, "l": 2 },
        "a": { "a": 0, "k": [440.363, -18.375, 0], "ix": 1, "l": 2 },
        "s": { "a": 0, "k": [100, 100, 100], "ix": 6, "l": 2 }
      },
      "ao": 0,
      "ef": [
        {
          "ty": 29,
          "nm": "Gaussian Blur",
          "np": 5,
          "mn": "ADBE Gaussian Blur 2",
          "ix": 1,
          "en": 1,
          "ef": [
            {
              "ty": 0,
              "nm": "Blurriness",
              "mn": "ADBE Gaussian Blur 2-0001",
              "ix": 1,
              "v": {
                "a": 1,
                "k": [
                  {
                    "i": { "x": [0.312], "y": [1] },
                    "o": { "x": [0.333], "y": [0] },
                    "t": 0,
                    "s": [90.5]
                  },
                  { "t": 14, "s": [0] }
                ],
                "ix": 1
              }
            },
            {
              "ty": 7,
              "nm": "Blur Dimensions",
              "mn": "ADBE Gaussian Blur 2-0002",
              "ix": 2,
              "v": { "a": 0, "k": 1, "ix": 2 }
            },
            {
              "ty": 7,
              "nm": "Repeat Edge Pixels",
              "mn": "ADBE Gaussian Blur 2-0003",
              "ix": 3,
              "v": { "a": 0, "k": 0, "ix": 3 }
            }
          ]
        }
      ],
      "t": {
        "d": {
          "k": [
            {
              "s": {
                "s": 49,
                "f": "Sora-Bold",
                "t": "Get Started with Our Flexible Plans",
                "ca": 0,
                "j": 0,
                "tr": 0,
                "lh": 58.8000030517578,
                "ls": 0,
                "fc": [0.094, 0.094, 0.106]
              },
              "t": 0
            }
          ]
        },
        "p": {},
        "m": { "g": 1, "a": { "a": 0, "k": [0, 0], "ix": 2 } },
        "a": []
      },
      "ip": 0,
      "op": 900,
      "st": 0,
      "ct": 1,
      "bm": 0
    },
    {
      "ddd": 0,
      "ind": 10,
      "ty": 3,
      "nm": "Path",
      "parent": 2,
      "sr": 1,
      "ks": {
        "o": { "a": 0, "k": 100, "ix": 11 },
        "r": { "a": 0, "k": 0, "ix": 10 },
        "p": { "a": 0, "k": [53.066, 37.948, 0], "ix": 2, "l": 2 },
        "a": { "a": 0, "k": [458.94, 46.749, 0], "ix": 1, "l": 2 },
        "s": { "a": 0, "k": [100, 100, 100], "ix": 6, "l": 2 }
      },
      "ao": 0,
      "ip": 0,
      "op": 900.900900900901,
      "st": 0,
      "ct": 1,
      "bm": 0
    }
  ],
  "markers": [],
  "chars": [
    {
      "ch": "G",
      "size": 49,
      "style": "Bold",
      "w": 83.1,
      "data": {
        "shapes": [
          {
            "ty": "gr",
            "it": [
              {
                "ind": 0,
                "ty": "sh",
                "ix": 1,
                "ks": {
                  "a": 0,
                  "k": {
                    "i": [
                      [-5.5, 2.7],
                      [-3.134, 5.067],
                      [0, 0],
                      [0, 0],
                      [0, 0],
                      [0, 0],
                      [3.333, -1.866],
                      [4.533, 0],
                      [2.766, 1.134],
                      [1.866, 2.1],
                      [0.966, 2.9],
                      [0, 3.534],
                      [-0.9, 2.834],
                      [-1.767, 2.067],
                      [-2.5, 1.134],
                      [-3.2, 0],
                      [-2.634, -1.133],
                      [-1.7, -2],
                      [-0.4, -2.666],
                      [0, 0],
                      [3.066, 4.3],
                      [5.066, 2.434],
                      [6.6, 0],
                      [4.633, -2.133],
                      [3.1, -3.6],
                      [1.533, -4.4],
                      [0, -4.6],
                      [0, 0],
                      [-1.534, -4.466],
                      [-3.167, -3.666],
                      [-4.867, -2.166],
                      [-6.534, 0]
                    ],
                    "o": [
                      [5.5, -2.7],
                      [0, 0],
                      [0, 0],
                      [0, 0],
                      [0, 0],
                      [-1.467, 3.067],
                      [-3.334, 1.867],
                      [-3.4, 0],
                      [-2.767, -1.133],
                      [-1.867, -2.1],
                      [-0.967, -2.9],
                      [0, -3.4],
                      [0.9, -2.833],
                      [1.766, -2.066],
                      [2.5, -1.133],
                      [3.333, 0],
                      [2.633, 1.134],
                      [1.7, 2],
                      [0, 0],
                      [-0.467, -5.666],
                      [-3.067, -4.3],
                      [-5.067, -2.433],
                      [-6.067, 0],
                      [-4.634, 2.134],
                      [-3.1, 3.6],
                      [-1.534, 4.4],
                      [0, 0],
                      [0, 4.467],
                      [1.533, 4.467],
                      [3.166, 3.667],
                      [4.866, 2.166],
                      [7.266, 0]
                    ],
                    "v": [
                      [61.95, -2.15],
                      [74.9, -13.8],
                      [74.9, -29.4],
                      [59.8, -29.4],
                      [59.8, -12],
                      [61.8, -23.2],
                      [54.6, -15.8],
                      [42.8, -13],
                      [33.55, -14.7],
                      [26.6, -19.55],
                      [22.35, -27.05],
                      [20.9, -36.7],
                      [22.25, -46.05],
                      [26.25, -53.4],
                      [32.65, -58.2],
                      [41.2, -59.9],
                      [50.15, -58.2],
                      [56.65, -53.5],
                      [59.8, -46.5],
                      [76.2, -46.5],
                      [70.9, -61.45],
                      [58.7, -71.55],
                      [41.2, -75.2],
                      [25.15, -72],
                      [13.55, -63.4],
                      [6.6, -51.4],
                      [4.3, -37.9],
                      [4.3, -35.7],
                      [6.6, -22.3],
                      [13.65, -10.1],
                      [25.7, -1.35],
                      [42.8, 1.9]
                    ],
                    "c": true
                  },
                  "ix": 2
                },
                "nm": "G",
                "mn": "ADBE Vector Shape - Group",
                "hd": false
              },
              {
                "ind": 1,
                "ty": "sh",
                "ix": 2,
                "ks": {
                  "a": 0,
                  "k": {
                    "i": [
                      [0, 0],
                      [0, 0],
                      [0, 0],
                      [0, 0]
                    ],
                    "o": [
                      [0, 0],
                      [0, 0],
                      [0, 0],
                      [0, 0]
                    ],
                    "v": [
                      [80.9, -26.2],
                      [80.9, -38],
                      [40.7, -38],
                      [40.7, -26.2]
                    ],
                    "c": true
                  },
                  "ix": 2
                },
                "nm": "G",
                "mn": "ADBE Vector Shape - Group",
                "hd": false
              }
            ],
            "nm": "G",
            "np": 5,
            "cix": 2,
            "bm": 0,
            "ix": 1,
            "mn": "ADBE Vector Group",
            "hd": false
          }
        ]
      },
      "fFamily": "Sora"
    },
    {
      "ch": "e",
      "size": 49,
      "style": "Bold",
      "w": 62.4,
      "data": {
        "shapes": [
          {
            "ty": "gr",
            "it": [
              {
                "ind": 0,
                "ty": "sh",
                "ix": 1,
                "ks": {
                  "a": 0,
                  "k": {
                    "i": [
                      [-3.534, 1.6],
                      [-2.334, 2.867],
                      [-0.8, 3.667],
                      [0, 0],
                      [1.866, -1.133],
                      [2.933, 0],
                      [2, 1.334],
                      [0.933, 2.434],
                      [0, 3.267],
                      [-1, 2.434],
                      [-1.934, 1.267],
                      [-2.8, 0],
                      [-1.834, -1.233],
                      [-0.934, -2.333],
                      [0, -3.266],
                      [0, 0],
                      [0, 0],
                      [0, 0],
                      [0, 0],
                      [0, 0],
                      [2.133, 4.234],
                      [4.033, 2.634],
                      [5.866, 0],
                      [3.5, -1.566],
                      [2.333, -2.666],
                      [1.233, -3.366],
                      [0, -3.666],
                      [0, 0],
                      [-1.234, -3.366],
                      [-2.367, -2.7],
                      [-3.567, -1.6],
                      [-4.667, 0]
                    ],
                    "o": [
                      [3.533, -1.6],
                      [2.333, -2.866],
                      [0, 0],
                      [-0.667, 1.667],
                      [-1.867, 1.134],
                      [-3.2, 0],
                      [-2, -1.333],
                      [-0.934, -2.433],
                      [0, -3.533],
                      [1, -2.433],
                      [1.933, -1.266],
                      [2.733, 0],
                      [1.833, 1.234],
                      [0.933, 2.334],
                      [0, 0],
                      [0, 0],
                      [0, 0],
                      [0, 0],
                      [0, 0],
                      [0, -5],
                      [-2.134, -4.233],
                      [-4.034, -2.633],
                      [-4.467, 0],
                      [-3.5, 1.567],
                      [-2.334, 2.667],
                      [-1.234, 3.367],
                      [0, 0],
                      [0, 3.534],
                      [1.233, 3.367],
                      [2.366, 2.7],
                      [3.566, 1.6],
                      [4.6, 0]
                    ],
                    "v": [
                      [44.6, -0.5],
                      [53.4, -7.2],
                      [58.1, -17],
                      [43.4, -17],
                      [39.6, -12.8],
                      [32.4, -11.1],
                      [24.6, -13.1],
                      [20.2, -18.75],
                      [18.8, -27.3],
                      [20.3, -36.25],
                      [24.7, -41.8],
                      [31.8, -43.7],
                      [38.65, -41.85],
                      [42.8, -36.5],
                      [44.2, -28.1],
                      [49.4, -32.3],
                      [10.6, -32.3],
                      [10.6, -23.2],
                      [59.1, -23.2],
                      [59.1, -28.6],
                      [55.9, -42.45],
                      [46.65, -52.75],
                      [31.8, -56.7],
                      [19.85, -54.35],
                      [11.1, -48],
                      [5.75, -38.95],
                      [3.9, -28.4],
                      [3.9, -26.4],
                      [5.75, -16.05],
                      [11.15, -6.95],
                      [20.05, -0.5],
                      [32.4, 1.9]
                    ],
                    "c": true
                  },
                  "ix": 2
                },
                "nm": "e",
                "mn": "ADBE Vector Shape - Group",
                "hd": false
              }
            ],
            "nm": "e",
            "np": 3,
            "cix": 2,
            "bm": 0,
            "ix": 1,
            "mn": "ADBE Vector Group",
            "hd": false
          }
        ]
      },
      "fFamily": "Sora"
    },
    {
      "ch": "t",
      "size": 49,
      "style": "Bold",
      "w": 43.4,
      "data": {
        "shapes": [
          {
            "ty": "gr",
            "it": [
              {
                "ind": 0,
                "ty": "sh",
                "ix": 1,
                "ks": {
                  "a": 0,
                  "k": {
                    "i": [
                      [0, 0],
                      [0, 0],
                      [0, 0],
                      [1.366, 1.367],
                      [0, 2.6],
                      [0, 0],
                      [0, 0],
                      [0, 0],
                      [-1.567, -3.233],
                      [-3.4, -1.366],
                      [-5.534, 0]
                    ],
                    "o": [
                      [0, 0],
                      [0, 0],
                      [-2.534, 0],
                      [-1.367, -1.366],
                      [0, 0],
                      [0, 0],
                      [0, 0],
                      [0, 5.534],
                      [1.566, 3.234],
                      [3.4, 1.366],
                      [0, 0]
                    ],
                    "v": [
                      [39.9, 0.7],
                      [39.9, -12.8],
                      [31.8, -12.8],
                      [25.95, -14.85],
                      [23.9, -20.8],
                      [23.9, -69.6],
                      [9, -69.6],
                      [9, -21.4],
                      [11.35, -8.25],
                      [18.8, -1.35],
                      [32.2, 0.7]
                    ],
                    "c": true
                  },
                  "ix": 2
                },
                "nm": "t",
                "mn": "ADBE Vector Shape - Group",
                "hd": false
              },
              {
                "ind": 1,
                "ty": "sh",
                "ix": 2,
                "ks": {
                  "a": 0,
                  "k": {
                    "i": [
                      [0, 0],
                      [0, 0],
                      [0, 0],
                      [0, 0]
                    ],
                    "o": [
                      [0, 0],
                      [0, 0],
                      [0, 0],
                      [0, 0]
                    ],
                    "v": [
                      [39.9, -43.1],
                      [39.9, -54.8],
                      [0.7, -54.8],
                      [0.7, -43.1]
                    ],
                    "c": true
                  },
                  "ix": 2
                },
                "nm": "t",
                "mn": "ADBE Vector Shape - Group",
                "hd": false
              }
            ],
            "nm": "t",
            "np": 5,
            "cix": 2,
            "bm": 0,
            "ix": 1,
            "mn": "ADBE Vector Group",
            "hd": false
          }
        ]
      },
      "fFamily": "Sora"
    },
    {
      "ch": " ",
      "size": 49,
      "style": "Bold",
      "w": 21,
      "data": {},
      "fFamily": "Sora"
    },
    {
      "ch": "S",
      "size": 49,
      "style": "Bold",
      "w": 66.7,
      "data": {
        "shapes": [
          {
            "ty": "gr",
            "it": [
              {
                "ind": 0,
                "ty": "sh",
                "ix": 1,
                "ks": {
                  "a": 0,
                  "k": {
                    "i": [
                      [-4.467, 1.933],
                      [-2.434, 3.5],
                      [0, 4.667],
                      [2.3, 3.167],
                      [4.066, 1.834],
                      [5.333, 0.467],
                      [0, 0],
                      [1.466, 1.534],
                      [0, 2.067],
                      [-0.8, 1.367],
                      [-1.634, 0.8],
                      [-2.4, 0],
                      [-1.7, -0.933],
                      [-0.867, -1.5],
                      [0, -1.8],
                      [0, 0],
                      [2.2, 3.567],
                      [4.1, 1.967],
                      [5.733, 0],
                      [4, -1.833],
                      [2.233, -3.4],
                      [0, -4.666],
                      [-4.334, -3.933],
                      [-7.267, -0.6],
                      [0, 0],
                      [-2, -1.366],
                      [0, -2.333],
                      [1.066, -1.433],
                      [2.066, -0.8],
                      [3.066, 0],
                      [2.133, 0.967],
                      [1.033, 1.6],
                      [0, 1.867],
                      [0, 0],
                      [-2.334, -3.633],
                      [-4.534, -2.1],
                      [-6.6, 0]
                    ],
                    "o": [
                      [4.466, -1.933],
                      [2.433, -3.5],
                      [0, -4.533],
                      [-2.3, -3.166],
                      [-4.067, -1.833],
                      [0, 0],
                      [-3.334, -0.266],
                      [-1.467, -1.533],
                      [0, -1.6],
                      [0.8, -1.366],
                      [1.633, -0.8],
                      [2.533, 0],
                      [1.7, 0.934],
                      [0.866, 1.5],
                      [0, 0],
                      [0, -4.8],
                      [-2.2, -3.566],
                      [-4.1, -1.966],
                      [-5.467, 0],
                      [-4, 1.834],
                      [-2.234, 3.4],
                      [0, 6.467],
                      [4.333, 3.934],
                      [0, 0],
                      [4.466, 0.4],
                      [2, 1.367],
                      [0, 1.867],
                      [-1.067, 1.434],
                      [-2.067, 0.8],
                      [-3.4, 0],
                      [-2.134, -0.966],
                      [-1.034, -1.6],
                      [0, 0],
                      [0, 4.734],
                      [2.333, 3.634],
                      [4.533, 2.1],
                      [6.2, 0]
                    ],
                    "v": [
                      [49.6, -1],
                      [59.95, -9.15],
                      [63.6, -21.4],
                      [60.15, -32.95],
                      [50.6, -40.45],
                      [36.5, -43.9],
                      [30.9, -44.4],
                      [23.7, -47.1],
                      [21.5, -52.5],
                      [22.7, -56.95],
                      [26.35, -60.2],
                      [32.4, -61.4],
                      [38.75, -60],
                      [42.6, -56.35],
                      [43.9, -51.4],
                      [59.9, -51.4],
                      [56.6, -63.95],
                      [47.15, -72.25],
                      [32.4, -75.2],
                      [18.2, -72.45],
                      [8.85, -64.6],
                      [5.5, -52.5],
                      [12, -36.9],
                      [29.4, -30.1],
                      [34.9, -29.6],
                      [44.6, -26.95],
                      [47.6, -21.4],
                      [46, -16.45],
                      [41.3, -13.1],
                      [33.6, -11.9],
                      [25.3, -13.35],
                      [20.55, -17.2],
                      [19, -22.4],
                      [3.1, -22.4],
                      [6.6, -9.85],
                      [16.9, -1.25],
                      [33.6, 1.9]
                    ],
                    "c": true
                  },
                  "ix": 2
                },
                "nm": "S",
                "mn": "ADBE Vector Shape - Group",
                "hd": false
              }
            ],
            "nm": "S",
            "np": 3,
            "cix": 2,
            "bm": 0,
            "ix": 1,
            "mn": "ADBE Vector Group",
            "hd": false
          }
        ]
      },
      "fFamily": "Sora"
    },
    {
      "ch": "a",
      "size": 49,
      "style": "Bold",
      "w": 59.4,
      "data": {
        "shapes": [
          {
            "ty": "gr",
            "it": [
              {
                "ind": 0,
                "ty": "sh",
                "ix": 1,
                "ks": {
                  "a": 0,
                  "k": {
                    "i": [
                      [0, 0],
                      [0, 0],
                      [2, 3.234],
                      [3.833, 1.6],
                      [5.6, 0],
                      [2.2, -0.066],
                      [2.066, -0.133],
                      [1.533, -0.133],
                      [0, 0],
                      [-2.534, 0.134],
                      [-2.4, 0.067],
                      [-1.467, 0],
                      [-1.334, -1.4],
                      [0, -2.8],
                      [0, 0],
                      [0, 0],
                      [0, 0]
                    ],
                    "o": [
                      [0, 0],
                      [0, -5.066],
                      [-2, -3.233],
                      [-3.834, -1.6],
                      [-1.934, 0],
                      [-2.2, 0.067],
                      [-2.067, 0.134],
                      [0, 0],
                      [2.066, -0.133],
                      [2.533, -0.133],
                      [2.4, -0.066],
                      [2.933, 0],
                      [1.333, 1.4],
                      [0, 0],
                      [0, 0],
                      [0, 0],
                      [0, 0]
                    ],
                    "v": [
                      [53.1, 0],
                      [53.1, -33.6],
                      [50.1, -46.05],
                      [41.35, -53.3],
                      [27.2, -55.7],
                      [21, -55.6],
                      [14.6, -55.3],
                      [9.2, -54.9],
                      [9.2, -41.4],
                      [16.1, -41.8],
                      [23.5, -42.1],
                      [29.3, -42.2],
                      [35.7, -40.1],
                      [37.7, -33.8],
                      [37.7, -16.2],
                      [40.4, -16.2],
                      [40.4, 0]
                    ],
                    "c": true
                  },
                  "ix": 2
                },
                "nm": "a",
                "mn": "ADBE Vector Shape - Group",
                "hd": false
              },
              {
                "ind": 1,
                "ty": "sh",
                "ix": 2,
                "ks": {
                  "a": 0,
                  "k": {
                    "i": [
                      [-2.634, 1.4],
                      [-1.5, 2.6],
                      [-0.334, 3.8],
                      [0, 0],
                      [0.933, -1.533],
                      [1.433, -0.633],
                      [1.8, 0],
                      [1.5, 1.367],
                      [0, 2.2],
                      [-1.5, 1.367],
                      [-2.8, 0],
                      [0, 0],
                      [0, 0],
                      [0, 0],
                      [3.733, -1.233],
                      [2.066, -2.566],
                      [0, -4],
                      [-1.667, -2.633],
                      [-2.967, -1.4],
                      [-3.934, 0]
                    ],
                    "o": [
                      [2.633, -1.4],
                      [1.5, -2.6],
                      [0, 0],
                      [-0.134, 2.734],
                      [-0.934, 1.534],
                      [-1.434, 0.634],
                      [-2.8, 0],
                      [-1.5, -1.366],
                      [0, -2.333],
                      [1.5, -1.366],
                      [0, 0],
                      [0, 0],
                      [0, 0],
                      [-4.867, 0],
                      [-3.734, 1.234],
                      [-2.067, 2.567],
                      [0, 3.667],
                      [1.666, 2.634],
                      [2.966, 1.4],
                      [3.8, 0]
                    ],
                    "v": [
                      [32.55, -0.7],
                      [38.75, -6.7],
                      [41.5, -16.3],
                      [37.7, -20.3],
                      [36.1, -13.9],
                      [32.55, -10.65],
                      [27.7, -9.7],
                      [21.25, -11.75],
                      [19, -17.1],
                      [21.25, -22.65],
                      [27.7, -24.7],
                      [39.5, -24.7],
                      [39.5, -33.6],
                      [27.8, -33.6],
                      [14.9, -31.75],
                      [6.2, -26.05],
                      [3.1, -16.2],
                      [5.6, -6.75],
                      [12.55, -0.7],
                      [22.9, 1.4]
                    ],
                    "c": true
                  },
                  "ix": 2
                },
                "nm": "a",
                "mn": "ADBE Vector Shape - Group",
                "hd": false
              }
            ],
            "nm": "a",
            "np": 5,
            "cix": 2,
            "bm": 0,
            "ix": 1,
            "mn": "ADBE Vector Group",
            "hd": false
          }
        ]
      },
      "fFamily": "Sora"
    },
    {
      "ch": "r",
      "size": 49,
      "style": "Bold",
      "w": 42.1,
      "data": {
        "shapes": [
          {
            "ty": "gr",
            "it": [
              {
                "ind": 0,
                "ty": "sh",
                "ix": 1,
                "ks": {
                  "a": 0,
                  "k": {
                    "i": [
                      [0, 0],
                      [0, 0],
                      [-2.4, 2.367],
                      [-4.4, 0],
                      [0, 0],
                      [0, 0],
                      [0, 0],
                      [3.3, -4.2],
                      [0, -7.733],
                      [0, 0],
                      [0, 0],
                      [0, 0],
                      [0, 0]
                    ],
                    "o": [
                      [0, 0],
                      [0, -4.466],
                      [2.4, -2.366],
                      [0, 0],
                      [0, 0],
                      [0, 0],
                      [-6.267, 0],
                      [-3.3, 4.2],
                      [0, 0],
                      [0, 0],
                      [0, 0],
                      [0, 0],
                      [0, 0]
                    ],
                    "v": [
                      [23.3, 0],
                      [23.3, -27.9],
                      [26.9, -38.15],
                      [37.1, -41.7],
                      [41.1, -41.7],
                      [41.1, -55.5],
                      [39, -55.5],
                      [24.65, -49.2],
                      [19.7, -31.3],
                      [20, -31.3],
                      [20, -54.8],
                      [7.3, -54.8],
                      [7.3, 0]
                    ],
                    "c": true
                  },
                  "ix": 2
                },
                "nm": "r",
                "mn": "ADBE Vector Shape - Group",
                "hd": false
              }
            ],
            "nm": "r",
            "np": 3,
            "cix": 2,
            "bm": 0,
            "ix": 1,
            "mn": "ADBE Vector Group",
            "hd": false
          }
        ]
      },
      "fFamily": "Sora"
    },
    {
      "ch": "d",
      "size": 49,
      "style": "Bold",
      "w": 70.3,
      "data": {
        "shapes": [
          {
            "ty": "gr",
            "it": [
              {
                "ind": 0,
                "ty": "sh",
                "ix": 1,
                "ks": {
                  "a": 0,
                  "k": {
                    "i": [
                      [-3.334, 1.9],
                      [-1.967, 3.667],
                      [-0.2, 5.2],
                      [0, 0],
                      [0, 0],
                      [0, 0],
                      [0, 0],
                      [0, 0],
                      [0, 0],
                      [0, 0],
                      [1.8, 3.7],
                      [3.2, 1.9],
                      [4.4, 0],
                      [3.133, -1.433],
                      [2.233, -2.566],
                      [1.166, -3.4],
                      [0, -3.933],
                      [0, 0],
                      [-1.234, -3.4],
                      [-2.334, -2.5],
                      [-3.167, -1.4],
                      [-3.867, 0]
                    ],
                    "o": [
                      [3.333, -1.9],
                      [1.966, -3.666],
                      [0, 0],
                      [0, 0],
                      [0, 0],
                      [0, 0],
                      [0, 0],
                      [0, 0],
                      [0, 0],
                      [-0.2, -5.4],
                      [-1.8, -3.7],
                      [-3.2, -1.9],
                      [-3.867, 0],
                      [-3.134, 1.434],
                      [-2.234, 2.567],
                      [-1.167, 3.4],
                      [0, 0],
                      [0, 3.934],
                      [1.233, 3.4],
                      [2.333, 2.5],
                      [3.166, 1.4],
                      [4.333, 0]
                    ],
                    "v": [
                      [41.4, -1.05],
                      [49.35, -9.4],
                      [52.6, -22.7],
                      [50.4, -22.7],
                      [50.4, 0],
                      [63.1, 0],
                      [63.1, -73],
                      [47, -73],
                      [47, -35.4],
                      [51.2, -31.5],
                      [48.2, -45.15],
                      [40.7, -53.55],
                      [29.3, -56.4],
                      [18.8, -54.25],
                      [10.75, -48.25],
                      [5.65, -39.3],
                      [3.9, -28.3],
                      [3.9, -26],
                      [5.75, -15],
                      [11.1, -6.15],
                      [19.35, -0.3],
                      [29.9, 1.8]
                    ],
                    "c": true
                  },
                  "ix": 2
                },
                "nm": "d",
                "mn": "ADBE Vector Shape - Group",
                "hd": false
              },
              {
                "ind": 1,
                "ty": "sh",
                "ix": 2,
                "ks": {
                  "a": 0,
                  "k": {
                    "i": [
                      [2.133, 1.267],
                      [1.2, 2.334],
                      [0, 3.2],
                      [-1.2, 2.367],
                      [-2.1, 1.367],
                      [-2.667, 0],
                      [-2.067, -1.066],
                      [-1.267, -2],
                      [0, -2.933],
                      [0, 0],
                      [1.233, -2.133],
                      [2.033, -1.1],
                      [2.466, 0]
                    ],
                    "o": [
                      [-2.134, -1.266],
                      [-1.2, -2.333],
                      [0, -3.133],
                      [1.2, -2.366],
                      [2.1, -1.366],
                      [2.4, 0],
                      [2.066, 1.067],
                      [1.266, 2],
                      [0, 0],
                      [0, 3],
                      [-1.234, 2.134],
                      [-2.034, 1.1],
                      [-2.667, 0]
                    ],
                    "v": [
                      [26.7, -13.5],
                      [21.7, -18.9],
                      [19.9, -27.2],
                      [21.7, -35.45],
                      [26.65, -41.05],
                      [33.8, -43.1],
                      [40.5, -41.5],
                      [45.5, -36.9],
                      [47.4, -29.5],
                      [47.4, -25.8],
                      [45.55, -18.1],
                      [40.65, -13.25],
                      [33.9, -11.6]
                    ],
                    "c": true
                  },
                  "ix": 2
                },
                "nm": "d",
                "mn": "ADBE Vector Shape - Group",
                "hd": false
              }
            ],
            "nm": "d",
            "np": 5,
            "cix": 2,
            "bm": 0,
            "ix": 1,
            "mn": "ADBE Vector Group",
            "hd": false
          }
        ]
      },
      "fFamily": "Sora"
    },
    {
      "ch": "w",
      "size": 49,
      "style": "Bold",
      "w": 92.2,
      "data": {
        "shapes": [
          {
            "ty": "gr",
            "it": [
              {
                "ind": 0,
                "ty": "sh",
                "ix": 1,
                "ks": {
                  "a": 0,
                  "k": {
                    "i": [
                      [0, 0],
                      [0, 0],
                      [0, 0],
                      [0, 0],
                      [0, 0],
                      [0, 0],
                      [0, 0],
                      [0, 0]
                    ],
                    "o": [
                      [0, 0],
                      [0, 0],
                      [0, 0],
                      [0, 0],
                      [0, 0],
                      [0, 0],
                      [0, 0],
                      [0, 0]
                    ],
                    "v": [
                      [38.6, 0],
                      [49.3, -52.6],
                      [42.2, -52.6],
                      [54.1, 0],
                      [66.5, 0],
                      [54.9, -53],
                      [37.4, -53],
                      [27.4, 0]
                    ],
                    "c": true
                  },
                  "ix": 2
                },
                "nm": "w",
                "mn": "ADBE Vector Shape - Group",
                "hd": false
              },
              {
                "ind": 1,
                "ty": "sh",
                "ix": 2,
                "ks": {
                  "a": 0,
                  "k": {
                    "i": [
                      [0, 0],
                      [0, 0],
                      [0, 0],
                      [0, 0]
                    ],
                    "o": [
                      [0, 0],
                      [0, 0],
                      [0, 0],
                      [0, 0]
                    ],
                    "v": [
                      [34.6, 0],
                      [34.5, -13.3],
                      [23.5, -13.3],
                      [23.6, 0]
                    ],
                    "c": true
                  },
                  "ix": 2
                },
                "nm": "w",
                "mn": "ADBE Vector Shape - Group",
                "hd": false
              },
              {
                "ind": 2,
                "ty": "sh",
                "ix": 3,
                "ks": {
                  "a": 0,
                  "k": {
                    "i": [
                      [0, 0],
                      [0, 0],
                      [0, 0],
                      [0, 0]
                    ],
                    "o": [
                      [0, 0],
                      [0, 0],
                      [0, 0],
                      [0, 0]
                    ],
                    "v": [
                      [31.1, 0],
                      [17.4, -54.8],
                      [1.7, -54.8],
                      [16.4, 0]
                    ],
                    "c": true
                  },
                  "ix": 2
                },
                "nm": "w",
                "mn": "ADBE Vector Shape - Group",
                "hd": false
              },
              {
                "ind": 3,
                "ty": "sh",
                "ix": 4,
                "ks": {
                  "a": 0,
                  "k": {
                    "i": [
                      [0, 0],
                      [0, 0],
                      [0, 0],
                      [0, 0]
                    ],
                    "o": [
                      [0, 0],
                      [0, 0],
                      [0, 0],
                      [0, 0]
                    ],
                    "v": [
                      [69.3, 0],
                      [69.3, -13.3],
                      [58.3, -13.3],
                      [58.2, 0]
                    ],
                    "c": true
                  },
                  "ix": 2
                },
                "nm": "w",
                "mn": "ADBE Vector Shape - Group",
                "hd": false
              },
              {
                "ind": 4,
                "ty": "sh",
                "ix": 5,
                "ks": {
                  "a": 0,
                  "k": {
                    "i": [
                      [0, 0],
                      [0, 0],
                      [0, 0],
                      [0, 0]
                    ],
                    "o": [
                      [0, 0],
                      [0, 0],
                      [0, 0],
                      [0, 0]
                    ],
                    "v": [
                      [76.4, 0],
                      [89.6, -54.8],
                      [74.9, -54.8],
                      [62.7, 0]
                    ],
                    "c": true
                  },
                  "ix": 2
                },
                "nm": "w",
                "mn": "ADBE Vector Shape - Group",
                "hd": false
              }
            ],
            "nm": "w",
            "np": 8,
            "cix": 2,
            "bm": 0,
            "ix": 1,
            "mn": "ADBE Vector Group",
            "hd": false
          }
        ]
      },
      "fFamily": "Sora"
    },
    {
      "ch": "i",
      "size": 49,
      "style": "Bold",
      "w": 33.4,
      "data": {
        "shapes": [
          {
            "ty": "gr",
            "it": [
              {
                "ind": 0,
                "ty": "sh",
                "ix": 1,
                "ks": {
                  "a": 0,
                  "k": {
                    "i": [
                      [0, 0],
                      [0, 0],
                      [0, 0],
                      [0, 0]
                    ],
                    "o": [
                      [0, 0],
                      [0, 0],
                      [0, 0],
                      [0, 0]
                    ],
                    "v": [
                      [25.9, 0],
                      [25.9, -54.8],
                      [9.9, -54.8],
                      [9.9, 0]
                    ],
                    "c": true
                  },
                  "ix": 2
                },
                "nm": "i",
                "mn": "ADBE Vector Shape - Group",
                "hd": false
              },
              {
                "ind": 1,
                "ty": "sh",
                "ix": 2,
                "ks": {
                  "a": 0,
                  "k": {
                    "i": [
                      [0, 0],
                      [0, 0],
                      [0, 0],
                      [0, 0]
                    ],
                    "o": [
                      [0, 0],
                      [0, 0],
                      [0, 0],
                      [0, 0]
                    ],
                    "v": [
                      [25.9, -43],
                      [25.9, -54.8],
                      [2.6, -54.8],
                      [2.6, -43]
                    ],
                    "c": true
                  },
                  "ix": 2
                },
                "nm": "i",
                "mn": "ADBE Vector Shape - Group",
                "hd": false
              },
              {
                "ind": 2,
                "ty": "sh",
                "ix": 3,
                "ks": {
                  "a": 0,
                  "k": {
                    "i": [
                      [-1.434, 1.567],
                      [0, 2.4],
                      [1.433, 1.567],
                      [3, 0],
                      [1.433, -1.566],
                      [0, -2.466],
                      [-1.434, -1.566],
                      [-3, 0]
                    ],
                    "o": [
                      [1.433, -1.566],
                      [0, -2.466],
                      [-1.434, -1.566],
                      [-3, 0],
                      [-1.434, 1.567],
                      [0, 2.4],
                      [1.433, 1.567],
                      [3, 0]
                    ],
                    "v": [
                      [22.75, -62.55],
                      [24.9, -68.5],
                      [22.75, -74.55],
                      [16.1, -76.9],
                      [9.45, -74.55],
                      [7.3, -68.5],
                      [9.45, -62.55],
                      [16.1, -60.2]
                    ],
                    "c": true
                  },
                  "ix": 2
                },
                "nm": "i",
                "mn": "ADBE Vector Shape - Group",
                "hd": false
              }
            ],
            "nm": "i",
            "np": 6,
            "cix": 2,
            "bm": 0,
            "ix": 1,
            "mn": "ADBE Vector Group",
            "hd": false
          }
        ]
      },
      "fFamily": "Sora"
    },
    {
      "ch": "h",
      "size": 49,
      "style": "Bold",
      "w": 65.2,
      "data": {
        "shapes": [
          {
            "ty": "gr",
            "it": [
              {
                "ind": 0,
                "ty": "sh",
                "ix": 1,
                "ks": {
                  "a": 0,
                  "k": {
                    "i": [
                      [0, 0],
                      [0, 0],
                      [-1.834, 1.934],
                      [-3, 0],
                      [-1.767, -1.833],
                      [0, -3],
                      [0, 0],
                      [0, 0],
                      [0, 0],
                      [3.2, 4.3],
                      [6.066, 0],
                      [0, 0],
                      [2.733, -1.966],
                      [1.4, -3.8],
                      [0, -5.533],
                      [0, 0],
                      [0, 0],
                      [0, 0],
                      [0, 0]
                    ],
                    "o": [
                      [0, 0],
                      [0, -3.2],
                      [1.833, -1.933],
                      [2.866, 0],
                      [1.766, 1.834],
                      [0, 0],
                      [0, 0],
                      [0, 0],
                      [0, -8.266],
                      [-3.2, -4.3],
                      [0, 0],
                      [-4.134, 0],
                      [-2.734, 1.967],
                      [-1.4, 3.8],
                      [0, 0],
                      [0, 0],
                      [0, 0],
                      [0, 0],
                      [0, 0]
                    ],
                    "v": [
                      [23.3, 0],
                      [23.3, -31.6],
                      [26.05, -39.3],
                      [33.3, -42.2],
                      [40.25, -39.45],
                      [42.9, -32.2],
                      [42.9, 0],
                      [58.9, 0],
                      [58.9, -31.2],
                      [54.1, -50.05],
                      [40.2, -56.5],
                      [39.5, -56.5],
                      [29.2, -53.55],
                      [23, -44.9],
                      [20.9, -30.9],
                      [23.3, -30.9],
                      [23.3, -73],
                      [7.3, -73],
                      [7.3, 0]
                    ],
                    "c": true
                  },
                  "ix": 2
                },
                "nm": "h",
                "mn": "ADBE Vector Shape - Group",
                "hd": false
              }
            ],
            "nm": "h",
            "np": 3,
            "cix": 2,
            "bm": 0,
            "ix": 1,
            "mn": "ADBE Vector Group",
            "hd": false
          }
        ]
      },
      "fFamily": "Sora"
    },
    {
      "ch": "O",
      "size": 49,
      "style": "Bold",
      "w": 86.4,
      "data": {
        "shapes": [
          {
            "ty": "gr",
            "it": [
              {
                "ind": 0,
                "ty": "sh",
                "ix": 1,
                "ks": {
                  "a": 0,
                  "k": {
                    "i": [
                      [-4.9, 2.3],
                      [-3.2, 3.767],
                      [-1.6, 4.4],
                      [0, 4.067],
                      [0, 0],
                      [1.666, 4.434],
                      [3.266, 3.6],
                      [4.866, 2.167],
                      [6.4, 0],
                      [4.866, -2.166],
                      [3.266, -3.6],
                      [1.633, -4.433],
                      [0, -4.533],
                      [0, 0],
                      [-1.567, -4.4],
                      [-3.2, -3.766],
                      [-4.9, -2.3],
                      [-6.6, 0]
                    ],
                    "o": [
                      [4.9, -2.3],
                      [3.2, -3.766],
                      [1.6, -4.4],
                      [0, 0],
                      [0, -4.533],
                      [-1.667, -4.433],
                      [-3.267, -3.6],
                      [-4.867, -2.166],
                      [-6.4, 0],
                      [-4.867, 2.167],
                      [-3.267, 3.6],
                      [-1.634, 4.434],
                      [0, 0],
                      [0, 4.067],
                      [1.566, 4.4],
                      [3.2, 3.767],
                      [4.9, 2.3],
                      [6.6, 0]
                    ],
                    "v": [
                      [60.45, -1.55],
                      [72.6, -10.65],
                      [79.8, -22.9],
                      [82.2, -35.6],
                      [82.2, -37.8],
                      [79.7, -51.25],
                      [72.3, -63.3],
                      [60.1, -71.95],
                      [43.2, -75.2],
                      [26.3, -71.95],
                      [14.1, -63.3],
                      [6.75, -51.25],
                      [4.3, -37.8],
                      [4.3, -35.6],
                      [6.65, -22.9],
                      [13.8, -10.65],
                      [25.95, -1.55],
                      [43.2, 1.9]
                    ],
                    "c": true
                  },
                  "ix": 2
                },
                "nm": "O",
                "mn": "ADBE Vector Shape - Group",
                "hd": false
              },
              {
                "ind": 1,
                "ty": "sh",
                "ix": 2,
                "ks": {
                  "a": 0,
                  "k": {
                    "i": [
                      [2.733, 1.2],
                      [1.966, 2.134],
                      [1, 2.8],
                      [0, 3.2],
                      [-1, 2.834],
                      [-1.967, 2.1],
                      [-2.734, 1.134],
                      [-3.467, 0],
                      [-2.734, -1.133],
                      [-1.967, -2.1],
                      [-1.034, -2.833],
                      [0, -3.4],
                      [1, -2.8],
                      [1.966, -2.133],
                      [2.766, -1.2],
                      [3.466, 0]
                    ],
                    "o": [
                      [-2.734, -1.2],
                      [-1.967, -2.133],
                      [-1, -2.8],
                      [0, -3.4],
                      [1, -2.833],
                      [1.966, -2.1],
                      [2.733, -1.133],
                      [3.466, 0],
                      [2.733, 1.134],
                      [1.966, 2.1],
                      [1.033, 2.834],
                      [0, 3.2],
                      [-1, 2.8],
                      [-1.967, 2.134],
                      [-2.767, 1.2],
                      [-3.467, 0]
                    ],
                    "v": [
                      [33.9, -15.2],
                      [26.85, -20.2],
                      [22.4, -27.6],
                      [20.9, -36.6],
                      [22.4, -45.95],
                      [26.85, -53.35],
                      [33.9, -58.2],
                      [43.2, -59.9],
                      [52.5, -58.2],
                      [59.55, -53.35],
                      [64.05, -45.95],
                      [65.6, -36.6],
                      [64.1, -27.6],
                      [59.65, -20.2],
                      [52.55, -15.2],
                      [43.2, -13.4]
                    ],
                    "c": true
                  },
                  "ix": 2
                },
                "nm": "O",
                "mn": "ADBE Vector Shape - Group",
                "hd": false
              }
            ],
            "nm": "O",
            "np": 5,
            "cix": 2,
            "bm": 0,
            "ix": 1,
            "mn": "ADBE Vector Group",
            "hd": false
          }
        ]
      },
      "fFamily": "Sora"
    },
    {
      "ch": "u",
      "size": 49,
      "style": "Bold",
      "w": 64.5,
      "data": {
        "shapes": [
          {
            "ty": "gr",
            "it": [
              {
                "ind": 0,
                "ty": "sh",
                "ix": 1,
                "ks": {
                  "a": 0,
                  "k": {
                    "i": [
                      [0, 0],
                      [-2.8, 1.8],
                      [-1.434, 3.7],
                      [0, 5.534],
                      [0, 0],
                      [0, 0],
                      [0, 0],
                      [0, 0],
                      [0, 0],
                      [0, 0],
                      [1.8, -1.8],
                      [2.866, 0],
                      [1.666, 1.734],
                      [0, 2.934],
                      [0, 0],
                      [0, 0],
                      [0, 0],
                      [-3.4, -4.1],
                      [-6.334, 0]
                    ],
                    "o": [
                      [4.133, 0],
                      [2.8, -1.8],
                      [1.433, -3.7],
                      [0, 0],
                      [0, 0],
                      [0, 0],
                      [0, 0],
                      [0, 0],
                      [0, 0],
                      [0, 3.067],
                      [-1.8, 1.8],
                      [-2.8, 0],
                      [-1.667, -1.733],
                      [0, 0],
                      [0, 0],
                      [0, 0],
                      [0, 8.267],
                      [3.4, 4.1],
                      [0, 0]
                    ],
                    "v": [
                      [26.5, 1.7],
                      [36.9, -1],
                      [43.25, -9.25],
                      [45.4, -23.1],
                      [44.3, -23.1],
                      [44.3, 0],
                      [57, 0],
                      [57, -54.8],
                      [41, -54.8],
                      [41, -22.6],
                      [38.3, -15.3],
                      [31.3, -12.6],
                      [24.6, -15.2],
                      [22.1, -22.2],
                      [22.1, -54.8],
                      [6.1, -54.8],
                      [6.1, -23],
                      [11.2, -4.45],
                      [25.8, 1.7]
                    ],
                    "c": true
                  },
                  "ix": 2
                },
                "nm": "u",
                "mn": "ADBE Vector Shape - Group",
                "hd": false
              }
            ],
            "nm": "u",
            "np": 3,
            "cix": 2,
            "bm": 0,
            "ix": 1,
            "mn": "ADBE Vector Group",
            "hd": false
          }
        ]
      },
      "fFamily": "Sora"
    },
    {
      "ch": "F",
      "size": 49,
      "style": "Bold",
      "w": 56,
      "data": {
        "shapes": [
          {
            "ty": "gr",
            "it": [
              {
                "ind": 0,
                "ty": "sh",
                "ix": 1,
                "ks": {
                  "a": 0,
                  "k": {
                    "i": [
                      [0, 0],
                      [0, 0],
                      [0, 0],
                      [0, 0]
                    ],
                    "o": [
                      [0, 0],
                      [0, 0],
                      [0, 0],
                      [0, 0]
                    ],
                    "v": [
                      [24.6, 0],
                      [24.6, -73],
                      [8.2, -73],
                      [8.2, 0]
                    ],
                    "c": true
                  },
                  "ix": 2
                },
                "nm": "F",
                "mn": "ADBE Vector Shape - Group",
                "hd": false
              },
              {
                "ind": 1,
                "ty": "sh",
                "ix": 2,
                "ks": {
                  "a": 0,
                  "k": {
                    "i": [
                      [0, 0],
                      [0, 0],
                      [0, 0],
                      [0, 0]
                    ],
                    "o": [
                      [0, 0],
                      [0, 0],
                      [0, 0],
                      [0, 0]
                    ],
                    "v": [
                      [50.8, -29.4],
                      [50.8, -43],
                      [22.6, -43],
                      [22.6, -29.4]
                    ],
                    "c": true
                  },
                  "ix": 2
                },
                "nm": "F",
                "mn": "ADBE Vector Shape - Group",
                "hd": false
              },
              {
                "ind": 2,
                "ty": "sh",
                "ix": 3,
                "ks": {
                  "a": 0,
                  "k": {
                    "i": [
                      [0, 0],
                      [0, 0],
                      [0, 0],
                      [0, 0]
                    ],
                    "o": [
                      [0, 0],
                      [0, 0],
                      [0, 0],
                      [0, 0]
                    ],
                    "v": [
                      [52, -59.4],
                      [52, -73],
                      [22.6, -73],
                      [22.6, -59.4]
                    ],
                    "c": true
                  },
                  "ix": 2
                },
                "nm": "F",
                "mn": "ADBE Vector Shape - Group",
                "hd": false
              }
            ],
            "nm": "F",
            "np": 6,
            "cix": 2,
            "bm": 0,
            "ix": 1,
            "mn": "ADBE Vector Group",
            "hd": false
          }
        ]
      },
      "fFamily": "Sora"
    },
    {
      "ch": "l",
      "size": 49,
      "style": "Bold",
      "w": 31.5,
      "data": {
        "shapes": [
          {
            "ty": "gr",
            "it": [
              {
                "ind": 0,
                "ty": "sh",
                "ix": 1,
                "ks": {
                  "a": 0,
                  "k": {
                    "i": [
                      [0, 0],
                      [0, 0],
                      [0, 0],
                      [0, 0]
                    ],
                    "o": [
                      [0, 0],
                      [0, 0],
                      [0, 0],
                      [0, 0]
                    ],
                    "v": [
                      [24.1, 0],
                      [24.1, -73],
                      [8, -73],
                      [8, 0]
                    ],
                    "c": true
                  },
                  "ix": 2
                },
                "nm": "l",
                "mn": "ADBE Vector Shape - Group",
                "hd": false
              },
              {
                "ind": 1,
                "ty": "sh",
                "ix": 2,
                "ks": {
                  "a": 0,
                  "k": {
                    "i": [
                      [0, 0],
                      [0, 0],
                      [0, 0],
                      [0, 0]
                    ],
                    "o": [
                      [0, 0],
                      [0, 0],
                      [0, 0],
                      [0, 0]
                    ],
                    "v": [
                      [24.1, -61.2],
                      [24.1, -73],
                      [1.5, -73],
                      [1.5, -61.2]
                    ],
                    "c": true
                  },
                  "ix": 2
                },
                "nm": "l",
                "mn": "ADBE Vector Shape - Group",
                "hd": false
              }
            ],
            "nm": "l",
            "np": 5,
            "cix": 2,
            "bm": 0,
            "ix": 1,
            "mn": "ADBE Vector Group",
            "hd": false
          }
        ]
      },
      "fFamily": "Sora"
    },
    {
      "ch": "x",
      "size": 49,
      "style": "Bold",
      "w": 60.1,
      "data": {
        "shapes": [
          {
            "ty": "gr",
            "it": [
              {
                "ind": 0,
                "ty": "sh",
                "ix": 1,
                "ks": {
                  "a": 0,
                  "k": {
                    "i": [
                      [0, 0],
                      [0, 0],
                      [0, 0],
                      [0, 0],
                      [0, 0],
                      [0, 0],
                      [0, 0],
                      [0, 0],
                      [0, 0],
                      [0, 0],
                      [0, 0],
                      [0, 0],
                      [0, 0],
                      [0, 0],
                      [0, 0],
                      [0, 0]
                    ],
                    "o": [
                      [0, 0],
                      [0, 0],
                      [0, 0],
                      [0, 0],
                      [0, 0],
                      [0, 0],
                      [0, 0],
                      [0, 0],
                      [0, 0],
                      [0, 0],
                      [0, 0],
                      [0, 0],
                      [0, 0],
                      [0, 0],
                      [0, 0],
                      [0, 0]
                    ],
                    "v": [
                      [17.4, 0],
                      [28.5, -19.9],
                      [30.1, -19.9],
                      [41.9, 0],
                      [59.3, 0],
                      [41.3, -28.8],
                      [40.9, -26.7],
                      [56.2, -54.8],
                      [39.9, -54.8],
                      [30.6, -36.2],
                      [29, -36.2],
                      [19.1, -54.8],
                      [1.8, -54.8],
                      [17.8, -26.9],
                      [18.2, -29.4],
                      [1.2, 0]
                    ],
                    "c": true
                  },
                  "ix": 2
                },
                "nm": "x",
                "mn": "ADBE Vector Shape - Group",
                "hd": false
              }
            ],
            "nm": "x",
            "np": 3,
            "cix": 2,
            "bm": 0,
            "ix": 1,
            "mn": "ADBE Vector Group",
            "hd": false
          }
        ]
      },
      "fFamily": "Sora"
    },
    {
      "ch": "b",
      "size": 49,
      "style": "Bold",
      "w": 70.3,
      "data": {
        "shapes": [
          {
            "ty": "gr",
            "it": [
              {
                "ind": 0,
                "ty": "sh",
                "ix": 1,
                "ks": {
                  "a": 0,
                  "k": {
                    "i": [
                      [-3.134, 1.433],
                      [-2.234, 2.567],
                      [-1.167, 3.4],
                      [0, 4],
                      [0, 0],
                      [1.166, 3.4],
                      [2.133, 2.5],
                      [3.033, 1.367],
                      [3.733, 0],
                      [3.333, -1.9],
                      [1.9, -3.766],
                      [0.2, -5.533],
                      [0, 0],
                      [0, 0],
                      [0, 0],
                      [0, 0],
                      [0, 0],
                      [0, 0],
                      [0, 0],
                      [-1.934, -3.6],
                      [-3.4, -1.9],
                      [-4.467, 0]
                    ],
                    "o": [
                      [3.133, -1.433],
                      [2.233, -2.566],
                      [1.166, -3.4],
                      [0, 0],
                      [0, -4],
                      [-1.167, -3.4],
                      [-2.134, -2.5],
                      [-3.034, -1.366],
                      [-4.267, 0],
                      [-3.334, 1.9],
                      [-1.9, 3.767],
                      [0, 0],
                      [0, 0],
                      [0, 0],
                      [0, 0],
                      [0, 0],
                      [0, 0],
                      [0, 0],
                      [0.133, 5.2],
                      [1.933, 3.6],
                      [3.4, 1.9],
                      [3.933, 0]
                    ],
                    "v": [
                      [51.6, -0.35],
                      [59.65, -6.35],
                      [64.75, -15.3],
                      [66.5, -26.4],
                      [66.5, -28.6],
                      [64.75, -39.7],
                      [59.8, -48.55],
                      [52.05, -54.35],
                      [41.9, -56.4],
                      [30.5, -53.55],
                      [22.65, -45.05],
                      [19.5, -31.1],
                      [23.3, -35.9],
                      [23.3, -73],
                      [7.3, -73],
                      [7.3, 0],
                      [20, 0],
                      [20, -22.5],
                      [18.1, -22.5],
                      [21.2, -9.3],
                      [29.2, -1.05],
                      [41, 1.8]
                    ],
                    "c": true
                  },
                  "ix": 2
                },
                "nm": "b",
                "mn": "ADBE Vector Shape - Group",
                "hd": false
              },
              {
                "ind": 1,
                "ty": "sh",
                "ix": 2,
                "ks": {
                  "a": 0,
                  "k": {
                    "i": [
                      [2.133, 1.067],
                      [1.366, 2.034],
                      [0, 2.867],
                      [0, 0],
                      [-1.3, 2.1],
                      [-2.134, 1.134],
                      [-2.4, 0],
                      [-2.034, -1.3],
                      [-1.134, -2.333],
                      [0, -3.133],
                      [1.133, -2.433],
                      [2.033, -1.333],
                      [2.733, 0]
                    ],
                    "o": [
                      [-2.134, -1.066],
                      [-1.367, -2.033],
                      [0, 0],
                      [0, -3],
                      [1.3, -2.1],
                      [2.133, -1.133],
                      [2.733, 0],
                      [2.033, 1.3],
                      [1.133, 2.334],
                      [0, 3.067],
                      [-1.134, 2.434],
                      [-2.034, 1.334],
                      [-2.267, 0]
                    ],
                    "v": [
                      [30.2, -13.2],
                      [24.95, -17.85],
                      [22.9, -25.2],
                      [22.9, -28.9],
                      [24.85, -36.55],
                      [30, -41.4],
                      [36.8, -43.1],
                      [43.95, -41.15],
                      [48.7, -35.7],
                      [50.4, -27.5],
                      [48.7, -19.25],
                      [43.95, -13.6],
                      [36.8, -11.6]
                    ],
                    "c": true
                  },
                  "ix": 2
                },
                "nm": "b",
                "mn": "ADBE Vector Shape - Group",
                "hd": false
              }
            ],
            "nm": "b",
            "np": 5,
            "cix": 2,
            "bm": 0,
            "ix": 1,
            "mn": "ADBE Vector Group",
            "hd": false
          }
        ]
      },
      "fFamily": "Sora"
    },
    {
      "ch": "P",
      "size": 49,
      "style": "Bold",
      "w": 66.7,
      "data": {
        "shapes": [
          {
            "ty": "gr",
            "it": [
              {
                "ind": 0,
                "ty": "sh",
                "ix": 1,
                "ks": {
                  "a": 0,
                  "k": {
                    "i": [
                      [0, 0],
                      [-4.434, 2.067],
                      [-2.367, 3.834],
                      [0, 5.2],
                      [0, 0],
                      [2.366, 3.8],
                      [4.433, 2.067],
                      [6.2, 0],
                      [0, 0],
                      [0, 0],
                      [0, 0],
                      [-1.834, -0.966],
                      [-1, -1.833],
                      [0, -2.533],
                      [1, -1.833],
                      [1.833, -1],
                      [2.533, 0],
                      [0, 0],
                      [0, 0]
                    ],
                    "o": [
                      [6.2, 0],
                      [4.433, -2.066],
                      [2.366, -3.833],
                      [0, 0],
                      [0, -5.333],
                      [-2.367, -3.8],
                      [-4.434, -2.066],
                      [0, 0],
                      [0, 0],
                      [0, 0],
                      [2.533, 0],
                      [1.833, 0.967],
                      [1, 1.834],
                      [0, 2.4],
                      [-1, 1.834],
                      [-1.834, 1],
                      [0, 0],
                      [0, 0],
                      [0, 0]
                    ],
                    "v": [
                      [34.9, -20.9],
                      [50.85, -24],
                      [61.05, -32.85],
                      [64.6, -46.4],
                      [64.6, -48],
                      [61.05, -61.7],
                      [50.85, -70.5],
                      [34.9, -73.6],
                      [22.6, -73.6],
                      [22.6, -59.4],
                      [35.7, -59.4],
                      [42.25, -57.95],
                      [46.5, -53.75],
                      [48, -47.2],
                      [46.5, -40.85],
                      [42.25, -36.6],
                      [35.7, -35.1],
                      [22.6, -35.1],
                      [22.6, -20.9]
                    ],
                    "c": true
                  },
                  "ix": 2
                },
                "nm": "P",
                "mn": "ADBE Vector Shape - Group",
                "hd": false
              },
              {
                "ind": 1,
                "ty": "sh",
                "ix": 2,
                "ks": {
                  "a": 0,
                  "k": {
                    "i": [
                      [0, 0],
                      [0, 0],
                      [0, 0],
                      [0, 0]
                    ],
                    "o": [
                      [0, 0],
                      [0, 0],
                      [0, 0],
                      [0, 0]
                    ],
                    "v": [
                      [24.6, 0],
                      [24.6, -73.6],
                      [8.2, -73.6],
                      [8.2, 0]
                    ],
                    "c": true
                  },
                  "ix": 2
                },
                "nm": "P",
                "mn": "ADBE Vector Shape - Group",
                "hd": false
              }
            ],
            "nm": "P",
            "np": 5,
            "cix": 2,
            "bm": 0,
            "ix": 1,
            "mn": "ADBE Vector Group",
            "hd": false
          }
        ]
      },
      "fFamily": "Sora"
    },
    {
      "ch": "n",
      "size": 49,
      "style": "Bold",
      "w": 65.2,
      "data": {
        "shapes": [
          {
            "ty": "gr",
            "it": [
              {
                "ind": 0,
                "ty": "sh",
                "ix": 1,
                "ks": {
                  "a": 0,
                  "k": {
                    "i": [
                      [0, 0],
                      [0, 0],
                      [-1.834, 1.9],
                      [-3, 0],
                      [-1.734, -1.866],
                      [0, -2.933],
                      [0, 0],
                      [0, 0],
                      [0, 0],
                      [3.366, 4.167],
                      [6.4, 0],
                      [0, 0],
                      [2.933, -1.866],
                      [1.433, -3.733],
                      [0, -5.6],
                      [0, 0],
                      [0, 0],
                      [0, 0],
                      [0, 0]
                    ],
                    "o": [
                      [0, 0],
                      [0, -3.066],
                      [1.833, -1.9],
                      [2.933, 0],
                      [1.733, 1.867],
                      [0, 0],
                      [0, 0],
                      [0, 0],
                      [0, -8.466],
                      [-3.367, -4.166],
                      [0, 0],
                      [-4.2, 0],
                      [-2.934, 1.867],
                      [-1.434, 3.734],
                      [0, 0],
                      [0, 0],
                      [0, 0],
                      [0, 0],
                      [0, 0]
                    ],
                    "v": [
                      [23.3, 0],
                      [23.3, -31.9],
                      [26.05, -39.35],
                      [33.3, -42.2],
                      [40.3, -39.4],
                      [42.9, -32.2],
                      [42.9, 0],
                      [58.9, 0],
                      [58.9, -31.3],
                      [53.85, -50.25],
                      [39.2, -56.5],
                      [38.5, -56.5],
                      [27.8, -53.7],
                      [21.25, -45.3],
                      [19.1, -31.3],
                      [20, -31.3],
                      [20, -54.8],
                      [7.3, -54.8],
                      [7.3, 0]
                    ],
                    "c": true
                  },
                  "ix": 2
                },
                "nm": "n",
                "mn": "ADBE Vector Shape - Group",
                "hd": false
              }
            ],
            "nm": "n",
            "np": 3,
            "cix": 2,
            "bm": 0,
            "ix": 1,
            "mn": "ADBE Vector Group",
            "hd": false
          }
        ]
      },
      "fFamily": "Sora"
    },
    {
      "ch": "s",
      "size": 49,
      "style": "Bold",
      "w": 55.6,
      "data": {
        "shapes": [
          {
            "ty": "gr",
            "it": [
              {
                "ind": 0,
                "ty": "sh",
                "ix": 1,
                "ks": {
                  "a": 0,
                  "k": {
                    "i": [
                      [-3.667, 1.433],
                      [-2, 2.7],
                      [0, 3.667],
                      [3.733, 3],
                      [6.733, 0.734],
                      [0, 0],
                      [1.266, 0.8],
                      [0, 1.534],
                      [-1.467, 0.934],
                      [-2.467, 0],
                      [-1.6, -1.233],
                      [-0.267, -1.8],
                      [0, 0],
                      [4.333, 3.1],
                      [7.066, 0],
                      [3.433, -1.333],
                      [1.933, -2.6],
                      [0, -3.866],
                      [-3.3, -3],
                      [-6.6, -0.666],
                      [0, 0],
                      [-1.4, -0.966],
                      [0, -1.6],
                      [1.833, -0.966],
                      [2.8, 0],
                      [1.833, 1.367],
                      [0.266, 1.734],
                      [0, 0],
                      [-4.4, -3.2],
                      [-7.8, 0]
                    ],
                    "o": [
                      [3.666, -1.433],
                      [2, -2.7],
                      [0, -5.066],
                      [-3.734, -3],
                      [0, 0],
                      [-2.867, -0.333],
                      [-1.267, -0.8],
                      [0, -1.6],
                      [1.466, -0.933],
                      [3.133, 0],
                      [1.6, 1.234],
                      [0, 0],
                      [-0.2, -5.866],
                      [-4.334, -3.1],
                      [-4.4, 0],
                      [-3.434, 1.334],
                      [-1.934, 2.6],
                      [0, 4.667],
                      [3.3, 3],
                      [0, 0],
                      [3.6, 0.4],
                      [1.4, 0.967],
                      [0, 1.8],
                      [-1.834, 0.967],
                      [-3.667, 0],
                      [-1.834, -1.366],
                      [0, 0],
                      [0.266, 5.8],
                      [4.4, 3.2],
                      [4.933, 0]
                    ],
                    "v": [
                      [41, -0.45],
                      [49.5, -6.65],
                      [52.5, -16.2],
                      [46.9, -28.3],
                      [31.2, -33.9],
                      [26.9, -34.3],
                      [20.7, -36],
                      [18.8, -39.5],
                      [21, -43.3],
                      [26.9, -44.7],
                      [34, -42.85],
                      [36.8, -38.3],
                      [51, -38.3],
                      [44.2, -51.75],
                      [27.1, -56.4],
                      [15.35, -54.4],
                      [7.3, -48.5],
                      [4.4, -38.8],
                      [9.35, -27.3],
                      [24.2, -21.8],
                      [28.5, -21.4],
                      [36, -19.35],
                      [38.1, -15.5],
                      [35.35, -11.35],
                      [28.4, -9.9],
                      [20.15, -11.95],
                      [17, -16.6],
                      [2.8, -16.6],
                      [9.8, -3.1],
                      [28.1, 1.7]
                    ],
                    "c": true
                  },
                  "ix": 2
                },
                "nm": "s",
                "mn": "ADBE Vector Shape - Group",
                "hd": false
              }
            ],
            "nm": "s",
            "np": 3,
            "cix": 2,
            "bm": 0,
            "ix": 1,
            "mn": "ADBE Vector Group",
            "hd": false
          }
        ]
      },
      "fFamily": "Sora"
    }
  ]
}
